.travis.yml
CHANGES.rst
MANIFEST.in
README.rst
TODO.rst
development.ini
production.ini
setup.cfg
setup.py
docs/Makefile
docs/source/conf.py
docs/source/index.rst
docs/source/models.rst
whiskers/__init__.py
whiskers/interfaces.py
whiskers/jsonwrapper.py
whiskers/models.py
whiskers.egg-info/PKG-INFO
whiskers.egg-info/SOURCES.txt
whiskers.egg-info/dependency_links.txt
whiskers.egg-info/entry_points.txt
whiskers.egg-info/not-zip-safe
whiskers.egg-info/requires.txt
whiskers.egg-info/top_level.txt
whiskers/scripts/__init__.py
whiskers/scripts/initializedb.py
whiskers/static/favicon.ico
whiskers/static/whiskers.css
whiskers/static/css/bootstrap-responsive.css
whiskers/static/css/bootstrap-responsive.min.css
whiskers/static/css/bootstrap.css
whiskers/static/css/bootstrap.min.css
whiskers/static/img/glyphicons-halflings-white.png
whiskers/static/img/glyphicons-halflings.png
whiskers/static/js/bootstrap.js
whiskers/static/js/bootstrap.min.js
whiskers/static/js/jquery-1.8.2.min.js
whiskers/static/js/whiskers.js
whiskers/tests/__init__.py
whiskers/tests/test_models.py
whiskers/tests/test_views.py
whiskers/tests/testdata.json
whiskers/views/__init__.py
whiskers/views/about.py
whiskers/views/buildouts.py
whiskers/views/hosts.py
whiskers/views/main.py
whiskers/views/packages.py
whiskers/views/settings.py
whiskers/views/version.py
whiskers/views/versions.py
whiskers/views/templates/about.pt
whiskers/views/templates/buildout.pt
whiskers/views/templates/buildouts.pt
whiskers/views/templates/host.pt
whiskers/views/templates/hosts.pt
whiskers/views/templates/main.pt
whiskers/views/templates/master.pt
whiskers/views/templates/package.pt
whiskers/views/templates/packages.pt
whiskers/views/templates/settings.pt
whiskers/views/templates/version.pt
whiskers/views/templates/versions.pt
whiskers/views/templates/view.pt