Metadata-Version: 1.1
Name: whiskers
Version: 1.0-alpha.3
Summary: whiskers
Home-page: https://github.com/pingviini/whiskers
Author: Jukka Ojaniemi
Author-email: jukka.ojaniemi@gmail.com
License: UNKNOWN
Keywords: web wsgi pyramid whiskers buildout
Platform: UNKNOWN
Classifier: Programming Language :: Python
Classifier: Programming Language :: Python :: 2.6
Classifier: Programming Language :: Python :: 2.7
Classifier: Programming Language :: Python :: 3.2
Classifier: Programming Language :: Python :: 3.3
Classifier: Framework :: Pyramid
Classifier: Topic :: Internet :: WWW/HTTP
Classifier: Topic :: Internet :: WWW/HTTP :: WSGI :: Application
